yt2mp3/__init__.py
yt2mp3/opts.py
yt2mp3/song.py
yt2mp3/util.py
yt2mp3-1.2.4.data/scripts/yt2mp3
yt2mp3-1.2.4.dist-info/LICENSE
yt2mp3-1.2.4.dist-info/METADATA
yt2mp3-1.2.4.dist-info/WHEEL
yt2mp3-1.2.4.dist-info/top_level.txt
yt2mp3-1.2.4.dist-info/RECORD
