Metadata-Version: 2.1
Name: yt2mp3
Version: 1.2.4
Summary: Simplifies the process of searching, downloading and converting Youtube videos to MP3 files
Home-page: https://github.com/tterb/yt2mp3
Author: Brett Stevenson
Author-email: bstevensondev@gmail.com
License: UNKNOWN
Download-URL: https://github.com/tterb/yt2mp3/archive/1.2.0.tar.gz
Keywords: youtube,convert,mp3,download,itunes,music,cli
Platform: UNKNOWN
Classifier: Development Status :: 4 - Beta
Classifier: Programming Language :: Python :: 3
Classifier: License :: OSI Approved :: MIT License
Classifier: Operating System :: OS Independent
Requires-Dist: beautifulsoup4 (==4.6.3)
Requires-Dist: colorama (==0.4.1)
Requires-Dist: curses-menu (==0.5.0)
Requires-Dist: itunespy (==1.5.5)
Requires-Dist: lxml (==4.2.5)
Requires-Dist: mutagen (==1.42.0)
Requires-Dist: Pillow (==5.3.0)
Requires-Dist: pydub (==0.23.0)
Requires-Dist: requests (==2.21.0)
Requires-Dist: setuptools (==40.6.3)
Requires-Dist: youtube-dl (==2018.12.17)
